pg_alchemy_kit/PG.py
pg_alchemy_kit/PGUtils.py
pg_alchemy_kit/PGUtilsBase.py
pg_alchemy_kit/PGUtilsORM.py
pg_alchemy_kit/__init__.py
pg_alchemy_kit/asyncio/__init__.py
pg_alchemy_kit/asyncio/pg.py
pg_alchemy_kit/asyncio/pg_utils.py
pg_alchemy_kit/cacheStrategies.py
pg_alchemy_kit-0.100.2.dist-info/METADATA
pg_alchemy_kit-0.100.2.dist-info/WHEEL
pg_alchemy_kit-0.100.2.dist-info/RECORD
