Metadata-Version: 2.1
Name: pg-alchemy-kit
Version: 0.100.2
Summary: A simple wrapper around sqlalchemy to make it easier to use with postgresql
Home-page: https://github.com/jsaied99/pg-alchemy-kit
Author: jsaied99
Author-email: jsaied99@gmail.com
Requires-Python: >=3.11,<4.0
Classifier: Programming Language :: Python :: 3
Classifier: Programming Language :: Python :: 3.11
Classifier: Programming Language :: Python :: 3.12
Requires-Dist: asyncpg (>=0.29.0,<0.30.0)
Requires-Dist: pandas (>=2.2.0,<3.0.0)
Requires-Dist: psycopg2-binary (==2.9.9)
Requires-Dist: pyarrow (>=15.0.0,<16.0.0)
Requires-Dist: sqlalchemy[asyncio] (>=2.0.27,<3.0.0)
Project-URL: Repository, https://github.com/jsaied99/pg-alchemy-kit
